{
  "eybSlug": "bali-4-8-for-sale-2024",
  "method": "slug",
  "sourceUrl": "https://europeanyachtbrokers.com/yachts/bali-4-8-for-sale-2024/",
  "wpPostId": 146258,
  "descriptionText": "Bali 4.8 for sale 2024 | 4 Guest Cabins + 1 Crew Cabin | Tax Excluded Bali 4.8 for sale 2024 — a practical and well-equipped catamaran in good condition, offered by Catana Group. This Bali 4.8 for sale 2024 is Italian-registered and built in 2024, presenting a modern cruising platform designed for comfortable life aboard and straightforward handling. She is in good condition and ready for inspection; the boat is visible in Sicily.Below is a clear specification list for quick reference - Bali 4.8 for sale 2024:GeneralManufacturer: Catana GroupModel: Bali 4.8Registration/Nature: Italian, registered (pleasure craft)Year of construction: 2024Safety certificate expiry: 2033Location: SicilyNote: Boat visible in SicilyDimensions & capacityOverall length: 14.86 mBeam: 7.88 mDraft: 1.35 mDisplacement: 22,000 kgNumber of owners: 1CE Certification / Passenger capacity: A12 / B14 / C24 / D40 / Category AHull & deckHull colour: WhiteHull material: GRP (vtr)Keel material / shape: GRP / skeg (scarponi)Cockpit teak: Yes (stern, steps, access)Upholstery: Complete — folding fore sunpad, flybridge cushions with backrests, foredeck cockpit cushions, helmsman seat cushions, flybridge seating cushionsBimini: Yes (fixed stainless frame + canvas)Cockpit tables: Yes (foredeck + flybridge)Notes: Teflon protections at stern, spring cleats at stern, integrated external BBQAccommodation & galleyDouble cabins: 4Double/twin cabin: 1 (with bunk bed)Crew cabin: 1Bathrooms: 5 (electric, freshwater)Showers: 5Interior wood finish: LightCooker: Yes (4 gas burners with pot retainers)Oven: YesFridge: Yes (American-style 635 l double door with freezer)Note: Separate skipper head and shower forward, bottle holder integrated into dinette table, front galley window opening, companionway/fore cockpit access door, folding transom, dishwasher (9 place), microwave, 12.5 kW generatorEngine & propulsionEngines: 2Type: InboardMake: YanmarModel: 4JH80Power: 80 hp x 2Engine year: 2025Fuel capacity: 1000 litresTransmission: s-drivePropellers: Fixed bladesSteering: WheelElectronics & navigationAutopilot: Yes (Raymarine P70)VHF: Yes (dual)Echo sounder: YesLog: YesCompass: YesPlotter: Yes (Axiom 7\" interior, 12\" exterior at helm)Wind instrument: YesNotes: Raymarine instrumentation, multi-display, AISElectrical & systemsVoltage: 12 / 220 VBatteries: 6 (4 gel + 2) — total 720 AhWater tanks: 2 (1+1) — total 1000 litres (GRP)Bilge pumps: 2 + 2 (automatic + manual)Heating: Yes (via inverter / air conditioning)Charger / inverter: YesAir conditioning: Yes (cabins, inverter hot/cold)Boiler: YesPressurised water (autoclave): YesBlack water: YesDeck shower: YesDesalinator: 230V, 240 l/hrRigging & anchoringMast: Aluminium, steppedWinches: 2Lazy bag: YesFurling jib: YesWindlass: Yes (with 70 m chain)Anchor: Yes (Delta)Mooring lines: YesLife raft: Yes (for 12 persons, expiry 2027)Fenders: 6This Bali 4.8 for sale 2024 is offered in good condition and represents a practical choice for buyers seeking generous living space, modern systems and comfortable cruising capability. For viewings or further technical information, the boat is currently located in Sicily.",
  "descriptionHtml": "<h3 style=\"text-align: center\"><strong><u>Bali 4.8 for sale 2024 | 4 Guest Cabins + 1 Crew Cabin | Tax Excluded</u><u><br> </u></strong></h3><p id=\"isPasted\"><strong>Bali 4.8 for sale 2024</strong>&nbsp;— a practical and well-equipped catamaran in good condition, offered by Catana Group. This Bali 4.8 for sale 2024 is Italian-registered and built in 2024, presenting a modern cruising platform designed for comfortable life aboard and straightforward handling. She is in good condition and ready for inspection; the boat is visible in Sicily.</p><p><strong><u>Below is a clear specification list for quick reference - Bali 4.8 for sale 2024:</u></strong></p><p>General</p><ul><li>Manufacturer: Catana Group</li><li>Model: Bali 4.8</li><li>Registration/Nature: Italian, registered (pleasure craft)</li><li>Year of construction: 2024</li><li>Safety certificate expiry: 2033</li><li>Location: Sicily</li><li>Note: Boat visible in Sicily</li></ul><p>Dimensions &amp; capacity</p><ul><li>Overall length: 14.86 m</li><li>Beam: 7.88 m</li><li>Draft: 1.35 m</li><li>Displacement: 22,000 kg</li><li>Number of owners: 1</li><li>CE Certification / Passenger capacity: A12 / B14 / C24 / D40 / Category A</li></ul><p>Hull &amp; deck</p><ul><li>Hull colour: White</li><li>Hull material: GRP (vtr)</li><li>Keel material / shape: GRP / skeg (scarponi)</li><li>Cockpit teak: Yes (stern, steps, access)</li><li>Upholstery: Complete — folding fore sunpad, flybridge cushions with backrests, foredeck cockpit cushions, helmsman seat cushions, flybridge seating cushions</li><li>Bimini: Yes (fixed stainless frame + canvas)</li><li>Cockpit tables: Yes (foredeck + flybridge)</li></ul><p>Notes: Teflon protections at stern, spring cleats at stern, integrated external BBQ</p><p>Accommodation &amp; galley</p><ul><li>Double cabins: 4</li><li>Double/twin cabin: 1 (with bunk bed)</li><li>Crew cabin: 1</li><li>Bathrooms: 5 (electric, freshwater)</li><li>Showers: 5</li><li>Interior wood finish: Light</li><li>Cooker: Yes (4 gas burners with pot retainers)</li><li>Oven: Yes</li><li>Fridge: Yes (American-style 635 l double door with freezer)</li></ul><p>Note: Separate skipper head and shower forward, bottle holder integrated into dinette table, front galley window opening, companionway/fore cockpit access door, folding transom, dishwasher (9 place), microwave, 12.5 kW generator</p><p>Engine &amp; propulsion</p><ul><li>Engines: 2</li><li>Type: Inboard</li><li>Make: Yanmar</li><li>Model: 4JH80</li><li>Power: 80 hp x 2</li><li>Engine year: 2025</li><li>Fuel capacity: 1000 litres</li><li>Transmission: s-drive</li><li>Propellers: Fixed blades</li><li>Steering: Wheel</li></ul><p>Electronics &amp; navigation</p><ul><li>Autopilot: Yes (Raymarine P70)</li><li>VHF: Yes (dual)</li><li>Echo sounder: Yes</li><li>Log: Yes</li><li>Compass: Yes</li><li>Plotter: Yes (Axiom 7\" interior, 12\" exterior at helm)</li><li>Wind instrument: Yes</li></ul><p>Notes: Raymarine instrumentation, multi-display, AIS</p><p>Electrical &amp; systems</p><ul><li>Voltage: 12 / 220 V</li><li>Batteries: 6 (4 gel + 2) — total 720 Ah</li><li>Water tanks: 2 (1+1) — total 1000 litres (GRP)</li><li>Bilge pumps: 2 + 2 (automatic + manual)</li><li>Heating: Yes (via inverter / air conditioning)</li><li>Charger / inverter: Yes</li><li>Air conditioning: Yes (cabins, inverter hot/cold)</li><li>Boiler: Yes</li><li>Pressurised water (autoclave): Yes</li><li>Black water: Yes</li><li>Deck shower: Yes</li><li>Desalinator: 230V, 240 l/hr</li></ul><p>Rigging &amp; anchoring</p><ul><li>Mast: Aluminium, stepped</li><li>Winches: 2</li><li>Lazy bag: Yes</li><li>Furling jib: Yes</li><li>Windlass: Yes (with 70 m chain)</li><li>Anchor: Yes (Delta)</li><li>Mooring lines: Yes</li><li>Life raft: Yes (for 12 persons, expiry 2027)</li><li>Fenders: 6</li></ul><p>This&nbsp;<strong>Bali 4.8 for sale 2024</strong>&nbsp;is offered in good condition and represents a practical choice for buyers seeking generous living space, modern systems and comfortable cruising capability. For viewings or further technical information, the boat is currently located in Sicily.</p>",
  "features": [
    "ais",
    "autopilot",
    "compass",
    "depth-sounder",
    "generator",
    "inverter",
    "plotter",
    "vhf",
    "wind-speed-and-direction",
    "air-conditioning",
    "battery-charger",
    "dishwasher",
    "manual-bilge-pump",
    "microwave",
    "oven",
    "refrigerator",
    "gangway",
    "liferaft",
    "fully-battened-mainsail",
    "furling-genoa"
  ],
  "featuredImage": "https://europeanyachtbrokers.com/wp-content/uploads/2026/01/1-1.jpg",
  "images": [
    {
      "id": 146270,
      "url": "https://europeanyachtbrokers.com/wp-content/uploads/2026/01/1-1.jpg",
      "width": 1920,
      "height": 1080
    },
    {
      "id": 146269,
      "url": "https://europeanyachtbrokers.com/wp-content/uploads/2026/01/11.jpg",
      "width": 1920,
      "height": 1080
    },
    {
      "id": 146268,
      "url": "https://europeanyachtbrokers.com/wp-content/uploads/2026/01/10.jpg",
      "width": 1920,
      "height": 1080
    },
    {
      "id": 146267,
      "url": "https://europeanyachtbrokers.com/wp-content/uploads/2026/01/9.jpg",
      "width": 1920,
      "height": 1080
    },
    {
      "id": 146266,
      "url": "https://europeanyachtbrokers.com/wp-content/uploads/2026/01/8.jpg",
      "width": 1920,
      "height": 1080
    },
    {
      "id": 146265,
      "url": "https://europeanyachtbrokers.com/wp-content/uploads/2026/01/7.jpg",
      "width": 1920,
      "height": 1080
    },
    {
      "id": 146264,
      "url": "https://europeanyachtbrokers.com/wp-content/uploads/2026/01/6.jpg",
      "width": 1920,
      "height": 1080
    },
    {
      "id": 146263,
      "url": "https://europeanyachtbrokers.com/wp-content/uploads/2026/01/5.jpg",
      "width": 1920,
      "height": 1080
    },
    {
      "id": 146262,
      "url": "https://europeanyachtbrokers.com/wp-content/uploads/2026/01/4.jpg",
      "width": 1920,
      "height": 1080
    },
    {
      "id": 146261,
      "url": "https://europeanyachtbrokers.com/wp-content/uploads/2026/01/3.jpg",
      "width": 1920,
      "height": 1080
    },
    {
      "id": 146260,
      "url": "https://europeanyachtbrokers.com/wp-content/uploads/2026/01/2.jpg",
      "width": 1920,
      "height": 1080
    }
  ]
}