{
  "eybSlug": "hallberg-rassy-36-for-sale-1999",
  "method": "slug",
  "sourceUrl": "https://europeanyachtbrokers.com/yachts/hallberg-rassy-36-for-sale-1999/",
  "wpPostId": 142996,
  "descriptionText": "Hallberg Rassy 36 for sale 1999 | 2 Cabins Version | Tax Paid The Hallberg Rassy 36 for sale 1999 is a highly respected Swedish cruiser, known for its solid build quality, comfortable interior, and reliable performance at sea (Autopilot, Compass, Radar, Plotter, Bow Thruster, Battery Charger, Hot Water,Tender, Liferaft...). This particular example is offered in good condition, reflecting the care of attentive ownership and regular maintenance. With classic proportions and thoughtful details throughout, she is ready for new adventures.Specifications – Hallberg Rassy 36 for sale 1999Length: 11.41 mBeam: 3.55 mDraft: 1.70 mHull Material: WoodKeel Material: LeadKeel Shape: FinDeck Equipment & ComfortSprayhood: Yes (new in 2023)Bimini: Yes (new in 2023)Cockpit Table: 2 (one removable)External Shower: YesCabins & InteriorDouble Cabins: 2Dinette Berth: 1Bathroom: 1Galley Stove: YesOven: YesRefrigerator: YesEngine & MechanicalEngine: Volvo Penta MD22Power: 50 hpEngine Year: 1999Engine Hours: 1,500Fuel Tank: 345 LTransmission: Shaft drivePropeller: 3 fixed bladesSteering: WheelBow Thruster: Yes (with new battery, 2024)Starter Motor: Recently replacedAnnual Engine Servicing: YesNavigation & ElectronicsAutopilot: YesVHF: YesLog: YesTridata: YesCompass: YesStereo: YesChart Plotter: YesRadar: YesWind Instrument: Yes (needs calibration)Raymarine Instrumentation: YesEpirb: Battery replacement neededElectrical & Water SystemsVoltage: 12/220 VBatteries: 3 (total 342 Ah)Water Tank: 1 (310 L, stainless steel)Bilge Pumps: 2 (automatic and manual)Battery Charger: YesBoiler (hot water): YesPressurised Water System: YesBlack Water System: YesRigging & SailsMast: SeldenBowsprit: YesSpinnaker Pole: YesWinches: 3 (Lewmar)Furling Mainsail (Selden): YesFurling Headsail (Furlex 2000): YesSails: New mainsail and headsail (2022), plus storm sail and small headsailAdditional EquipmentTender: YesOutboard: YesAnchor: CQR 15 kgChain: 60 mMooring Lines: YesLiferaft: Yes (expires 2029)Fenders: 8All essential maintenance has been attended to, and key mechanical items such as the starter motor and bow thruster battery are recently renewed.The Hallberg Rassy 36 for sale 1999 combines timeless design with modern equipment and practical amenities for comfortable voyaging. With updated sails, recent sprayhood and bimini, and a host of navigational equipment, she is well prepared for her next owner. Viewing available, don't hesitate to contact us!",
  "descriptionHtml": "<h4 style=\"text-align: center\"><strong>Hallberg Rassy 36 for sale 1999 | 2 Cabins Version | Tax Paid</strong></h4><p>&nbsp;</p><p>The <strong>Hallberg Rassy 36 for sale 1999</strong> is a highly respected Swedish cruiser, known for its solid build quality, comfortable interior, and reliable performance at sea <strong><em>(Autopilot, Compass, Radar, Plotter, Bow Thruster, Battery Charger, Hot Water,Tender, Liferaft...</em>)</strong>. This particular example is offered in good condition, reflecting the care of attentive ownership and regular maintenance. With classic proportions and thoughtful details throughout, she is ready for new adventures.</p><p><strong>Specifications – Hallberg Rassy 36 for sale 1999</strong></p><ul><li><strong>Length:</strong> 11.41 m</li><li><strong>Beam:</strong> 3.55 m</li><li><strong>Draft:</strong> 1.70 m</li><li><strong>Hull Material:</strong> Wood</li><li><strong>Keel Material:</strong> Lead</li><li><strong>Keel Shape:</strong> Fin</li></ul><p><strong>Deck Equipment &amp; Comfort</strong></p><ul><li><strong>Sprayhood:</strong> Yes (new in 2023)</li><li><strong>Bimini:</strong> Yes (new in 2023)</li><li><strong>Cockpit Table:</strong> 2 (one removable)</li><li><strong>External Shower:</strong> Yes</li></ul><p><strong>Cabins &amp; Interior</strong></p><ul><li><strong>Double Cabins:</strong> 2</li><li><strong>Dinette Berth:</strong> 1</li><li><strong>Bathroom:</strong> 1</li><li><strong>Galley Stove:</strong> Yes</li><li><strong>Oven:</strong> Yes</li><li><strong>Refrigerator:</strong> Yes</li></ul><p><strong>Engine &amp; Mechanical</strong></p><ul><li><strong>Engine:</strong> Volvo Penta MD22</li><li><strong>Power:</strong> 50 hp</li><li><strong>Engine Year:</strong> 1999</li><li><strong>Engine Hours:</strong> 1,500</li><li><strong>Fuel Tank:</strong> 345 L</li><li><strong>Transmission:</strong> Shaft drive</li><li><strong>Propeller:</strong> 3 fixed blades</li><li><strong>Steering:</strong> Wheel</li><li><strong>Bow Thruster:</strong> Yes (with new battery, 2024)</li><li><strong>Starter Motor:</strong> Recently replaced</li><li><strong>Annual Engine Servicing:</strong> Yes</li></ul><p><strong>Navigation &amp; Electronics</strong></p><ul><li><strong>Autopilot:</strong> Yes</li><li><strong>VHF:</strong> Yes</li><li><strong>Log:</strong> Yes</li><li><strong>Tridata:</strong> Yes</li><li><strong>Compass:</strong> Yes</li><li><strong>Stereo:</strong> Yes</li><li><strong>Chart Plotter:</strong> Yes</li><li><strong>Radar:</strong> Yes</li><li><strong>Wind Instrument:</strong> Yes (needs calibration)</li><li><strong>Raymarine Instrumentation:</strong> Yes</li><li><strong>Epirb:</strong> Battery replacement needed</li></ul><p><strong>Electrical &amp; Water Systems</strong></p><ul><li><strong>Voltage:</strong> 12/220 V</li><li><strong>Batteries:</strong> 3 (total 342 Ah)</li><li><strong>Water Tank:</strong> 1 (310 L, stainless steel)</li><li><strong>Bilge Pumps:</strong> 2 (automatic and manual)</li><li><strong>Battery Charger:</strong> Yes</li><li><strong>Boiler (hot water):</strong> Yes</li><li><strong>Pressurised Water System:</strong> Yes</li><li><strong>Black Water System:</strong> Yes</li></ul><p><strong>Rigging &amp; Sails</strong></p><ul><li><strong>Mast:</strong> Selden</li><li><strong>Bowsprit:</strong> Yes</li><li><strong>Spinnaker Pole:</strong> Yes</li><li><strong>Winches:</strong> 3 (Lewmar)</li><li><strong>Furling Mainsail (Selden):</strong> Yes</li><li><strong>Furling Headsail (Furlex 2000):</strong> Yes</li><li><strong>Sails:</strong> New mainsail and headsail (2022), plus storm sail and small headsail</li></ul><p><strong>Additional Equipment</strong></p><ul><li><strong>Tender:</strong> Yes</li><li><strong>Outboard:</strong> Yes</li><li><strong>Anchor:</strong> CQR 15 kg</li><li><strong>Chain:</strong> 60 m</li><li><strong>Mooring Lines:</strong> Yes</li><li><strong>Liferaft:</strong> Yes (expires 2029)</li><li><strong>Fenders:</strong> 8</li></ul><p>All essential maintenance has been attended to, and key mechanical items such as the starter motor and bow thruster battery are recently renewed.</p><p>The <strong>Hallberg Rassy 36 for sale 1999</strong> combines timeless design with modern equipment and practical amenities for comfortable voyaging. With updated sails, recent sprayhood and bimini, and a host of navigational equipment, she is well prepared for her next owner. Viewing available, don't hesitate to contact us!</p>",
  "features": [
    "autopilot",
    "cockpit-speakers",
    "compass",
    "log-speedometer",
    "plotter",
    "radar",
    "radio",
    "vhf",
    "wind-speed-and-direction",
    "battery-charger",
    "bow-thruster",
    "hot-water",
    "oven",
    "refrigerator",
    "liferaft",
    "outboard-engine-brackets",
    "tender",
    "furling-genoa",
    "furling-mainsail",
    "spinnaker"
  ],
  "featuredImage": "https://europeanyachtbrokers.com/wp-content/uploads/2025/11/1-4.jpg",
  "images": [
    {
      "id": 143048,
      "url": "https://europeanyachtbrokers.com/wp-content/uploads/2025/11/1-4.jpg",
      "width": 1920,
      "height": 1080
    },
    {
      "id": 143020,
      "url": "https://europeanyachtbrokers.com/wp-content/uploads/2025/11/11-1.jpg",
      "width": 1920,
      "height": 1080
    },
    {
      "id": 143018,
      "url": "https://europeanyachtbrokers.com/wp-content/uploads/2025/11/10-1.jpg",
      "width": 1920,
      "height": 1080
    },
    {
      "id": 143016,
      "url": "https://europeanyachtbrokers.com/wp-content/uploads/2025/11/9-1.jpg",
      "width": 1920,
      "height": 1080
    },
    {
      "id": 143014,
      "url": "https://europeanyachtbrokers.com/wp-content/uploads/2025/11/8-1.jpg",
      "width": 1920,
      "height": 1080
    },
    {
      "id": 143012,
      "url": "https://europeanyachtbrokers.com/wp-content/uploads/2025/11/7-1.jpg",
      "width": 1920,
      "height": 1080
    },
    {
      "id": 143010,
      "url": "https://europeanyachtbrokers.com/wp-content/uploads/2025/11/6-1.jpg",
      "width": 1920,
      "height": 1080
    },
    {
      "id": 143008,
      "url": "https://europeanyachtbrokers.com/wp-content/uploads/2025/11/5-1.jpg",
      "width": 1920,
      "height": 1080
    },
    {
      "id": 143006,
      "url": "https://europeanyachtbrokers.com/wp-content/uploads/2025/11/4-1.jpg",
      "width": 1920,
      "height": 1080
    },
    {
      "id": 143003,
      "url": "https://europeanyachtbrokers.com/wp-content/uploads/2025/11/3-1.jpg",
      "width": 1920,
      "height": 1080
    },
    {
      "id": 143001,
      "url": "https://europeanyachtbrokers.com/wp-content/uploads/2025/11/2-1.jpg",
      "width": 1920,
      "height": 1080
    }
  ]
}