{
  "eybSlug": "lagoon-42-for-sale-2020",
  "method": "slug",
  "sourceUrl": "https://europeanyachtbrokers.com/yachts/lagoon-42-for-sale-2020/",
  "wpPostId": 146271,
  "descriptionText": "Lagoon 42 for sale 2020 | 3 Guest Cabins - Owner's Version | Vat PaidThis Lagoon 42 for sale 2020 in Athens, Greece, presents an appealing opportunity for liveaboard enthusiasts and long-distance sailors alike. Registered under the French flag with VAT paid, this vessel benefits from careful ownership, having never been chartered and maintained to a high standard.The catamaran is thoughtfully equipped for living aboard and longer passages, featuring modern upgrades including lithium batteries, Victron energy management, and solar panels. The addition of a watermaker supports off-grid cruising, while the upgraded sail inventory—with Code 0 and asymmetric spinnaker—provides sailing versatility.(Autopilot, Radar, Plotter, Inverter, Solar Panels, Watermaker, Davits, Tender...)Specifications at a GlanceLocation: Athens, GreeceYear: 2020Length overall: 12.8 mMaximum draught: 1.25 mBeam: 7.68 mFlag of Registry: FranceTax Status: VAT PaidDry Weight: 12,104 kgDisplacement: 18 tFuel tank: 600 lWater tank: 600 lHolding tank capacity: 240 lCruising speed: 6-7 knotsMaximum speed: 12 knotsEngineMake: YanmarModel: 4JH57Year: 2020Power: 57 hpMotor hours: 1000Propellers: FixedDrive type: Sail DriveSail InventoryFully battened mainsailFurling GenoaGennaker / Cruising SpinnakerAsymmetric SpinnakerElectronicsDepth sounderLog speedWind speed and directionChartplotterAutopilotCompassGPSVHFRadarComputerTVCockpit speakersInterior EquipmentWashing machineOvenMicrowaveMarine and electric headsRefrigeratorDeep freezerBattery chargerElectric and manual bilge pumpsHot waterFresh water makerSea water pumpElectrical & RiggingShore power inletInverterSteering wheelElectric winchSpinnaker poleExterior FeaturesTeak cockpitGangwaySolar panelsCockpit cushionsSwimming ladderCockpit showerDavitsTenderLiferaftCockpit tableCoversBimini topMainsail coverCockpit coverSprayhoodLazy bagLazy jacksThis Lagoon 42 for sale 2020 represents a straightforward ownership history with just one previous owner and no commercial charter use. With VAT paid and a possibility to continue the current leasing (subject to eligibility), it provides an accessible route into European cruising. The vessel is in good condition and is well-equipped for extended voyaging or living aboard in comfort. If you’re looking for a reliable and well-specified Lagoon 42, available in Athens, this boat is worth your serious consideration.",
  "descriptionHtml": "<h3 id=\"isPasted\" style=\"text-align: center\"><strong>Lagoon 42 for sale 2020 | 3 Guest Cabins - Owner's Version | Vat Paid</strong></h3><p>This&nbsp;<strong>Lagoon 42 for sale 2020</strong>&nbsp;in Athens, Greece, presents an appealing opportunity for liveaboard enthusiasts and long-distance sailors alike. Registered under the French flag with VAT paid, this vessel benefits from careful ownership, having never been chartered and maintained to a high standard.</p><p>The catamaran is thoughtfully equipped for living aboard and longer passages, featuring modern upgrades including lithium batteries, Victron energy management, and solar panels. The addition of a watermaker supports off-grid cruising, while the upgraded sail inventory—with Code 0 and asymmetric spinnaker—provides sailing versatility.</p><p><strong><em>(Autopilot, Radar, Plotter, Inverter, Solar Panels, Watermaker, Davits, Tender...)</em></strong></p><p><strong>Specifications at a Glance</strong></p><ul><li><strong>Location:</strong>&nbsp;Athens, Greece</li><li><strong>Year:</strong>&nbsp;2020</li><li><strong>Length overall:</strong>&nbsp;12.8 m</li><li><strong>Maximum draught:</strong>&nbsp;1.25 m</li><li><strong>Beam:</strong>&nbsp;7.68 m</li><li><strong>Flag of Registry:</strong>&nbsp;France</li><li><strong>Tax Status:</strong>&nbsp;VAT Paid</li><li><strong>Dry Weight:</strong>&nbsp;12,104 kg</li><li><strong>Displacement:</strong>&nbsp;18 t</li><li><strong>Fuel tank:</strong>&nbsp;600 l</li><li><strong>Water tank:</strong>&nbsp;600 l</li><li><strong>Holding tank capacity:</strong>&nbsp;240 l</li><li><strong>Cruising speed:</strong>&nbsp;6-7 knots</li><li><strong>Maximum speed:</strong>&nbsp;12 knots</li></ul><p><strong>Engine</strong></p><ul><li><strong>Make:</strong>&nbsp;Yanmar</li><li><strong>Model:</strong>&nbsp;4JH57</li><li><strong>Year:</strong>&nbsp;2020</li><li><strong>Power:</strong>&nbsp;57 hp</li><li><strong>Motor hours:</strong>&nbsp;1000</li><li><strong>Propellers:</strong>&nbsp;Fixed</li><li><strong>Drive type:</strong>&nbsp;Sail Drive</li></ul><p><strong>Sail Inventory</strong></p><ul><li>Fully battened mainsail</li><li>Furling Genoa</li><li>Gennaker / Cruising Spinnaker</li><li>Asymmetric Spinnaker</li></ul><p><strong>Electronics</strong></p><ul><li>Depth sounder</li><li>Log speed</li><li>Wind speed and direction</li><li>Chartplotter</li><li>Autopilot</li><li>Compass</li><li>GPS</li><li>VHF</li><li>Radar</li><li>Computer</li><li>TV</li><li>Cockpit speakers</li></ul><p><strong>Interior Equipment</strong></p><ul><li>Washing machine</li><li>Oven</li><li>Microwave</li><li>Marine and electric heads</li><li>Refrigerator</li><li>Deep freezer</li><li>Battery charger</li><li>Electric and manual bilge pumps</li><li>Hot water</li><li>Fresh water maker</li><li>Sea water pump</li></ul><p><strong>Electrical &amp; Rigging</strong></p><ul><li>Shore power inlet</li><li>Inverter</li><li>Steering wheel</li><li>Electric winch</li><li>Spinnaker pole</li></ul><p><strong>Exterior Features</strong></p><ul><li>Teak cockpit</li><li>Gangway</li><li>Solar panels</li><li>Cockpit cushions</li><li>Swimming ladder</li><li>Cockpit shower</li><li>Davits</li><li>Tender</li><li>Liferaft</li><li>Cockpit table</li></ul><p><strong>Covers</strong></p><ul><li>Bimini top</li><li>Mainsail cover</li><li>Cockpit cover</li><li>Sprayhood</li><li>Lazy bag</li><li>Lazy jacks</li></ul><p>This&nbsp;<strong>Lagoon 42 for sale 2020</strong>&nbsp;represents a straightforward ownership history with just one previous owner and no commercial charter use. With VAT paid and a possibility to continue the current leasing (subject to eligibility), it provides an accessible route into European cruising. The vessel is in good condition and is well-equipped for extended voyaging or living aboard in comfort. If you’re looking for a reliable and well-specified Lagoon 42, available in Athens, this boat is worth your serious consideration.</p>",
  "features": [
    "autopilot",
    "cockpit-speakers",
    "compass",
    "computer",
    "depth-sounder",
    "gps",
    "inverter",
    "log-speedometer",
    "plotter",
    "radar",
    "tv-set",
    "vhf",
    "wind-speed-and-direction",
    "battery-charger",
    "deep-freezer",
    "electric-bilge-pump",
    "electric-head",
    "fresh-water-maker",
    "hot-water",
    "manual-bilge-pump",
    "marine-head",
    "microwave",
    "oven",
    "refrigerator",
    "sea-water-pump",
    "washing-machine",
    "davits",
    "gangway",
    "liferaft",
    "solar-panels",
    "swimming-ladder",
    "tender",
    "asymetric-spinnaker",
    "fully-battened-mainsail",
    "furling-genoa",
    "gennaker"
  ],
  "featuredImage": "https://europeanyachtbrokers.com/wp-content/uploads/2026/01/1-4.jpg",
  "images": [
    {
      "id": 146390,
      "url": "https://europeanyachtbrokers.com/wp-content/uploads/2026/01/1-4.jpg",
      "width": 1920,
      "height": 1080
    },
    {
      "id": 146318,
      "url": "https://europeanyachtbrokers.com/wp-content/uploads/2026/01/47.jpg",
      "width": 1920,
      "height": 1080
    },
    {
      "id": 146317,
      "url": "https://europeanyachtbrokers.com/wp-content/uploads/2026/01/46.jpg",
      "width": 1920,
      "height": 1080
    },
    {
      "id": 146316,
      "url": "https://europeanyachtbrokers.com/wp-content/uploads/2026/01/45.jpg",
      "width": 1920,
      "height": 1080
    },
    {
      "id": 146315,
      "url": "https://europeanyachtbrokers.com/wp-content/uploads/2026/01/44.jpg",
      "width": 1920,
      "height": 1080
    },
    {
      "id": 146314,
      "url": "https://europeanyachtbrokers.com/wp-content/uploads/2026/01/43.jpg",
      "width": 1920,
      "height": 1080
    },
    {
      "id": 146313,
      "url": "https://europeanyachtbrokers.com/wp-content/uploads/2026/01/42.jpg",
      "width": 1920,
      "height": 1080
    },
    {
      "id": 146312,
      "url": "https://europeanyachtbrokers.com/wp-content/uploads/2026/01/41.jpg",
      "width": 1920,
      "height": 1080
    },
    {
      "id": 146311,
      "url": "https://europeanyachtbrokers.com/wp-content/uploads/2026/01/40.jpg",
      "width": 1920,
      "height": 1080
    },
    {
      "id": 146310,
      "url": "https://europeanyachtbrokers.com/wp-content/uploads/2026/01/39.jpg",
      "width": 1920,
      "height": 1080
    },
    {
      "id": 146309,
      "url": "https://europeanyachtbrokers.com/wp-content/uploads/2026/01/38.jpg",
      "width": 1920,
      "height": 1080
    },
    {
      "id": 146308,
      "url": "https://europeanyachtbrokers.com/wp-content/uploads/2026/01/37.jpg",
      "width": 1920,
      "height": 1080
    },
    {
      "id": 146307,
      "url": "https://europeanyachtbrokers.com/wp-content/uploads/2026/01/36.jpg",
      "width": 1920,
      "height": 1080
    },
    {
      "id": 146306,
      "url": "https://europeanyachtbrokers.com/wp-content/uploads/2026/01/35.jpg",
      "width": 1920,
      "height": 1080
    },
    {
      "id": 146305,
      "url": "https://europeanyachtbrokers.com/wp-content/uploads/2026/01/34.jpg",
      "width": 1920,
      "height": 1080
    },
    {
      "id": 146304,
      "url": "https://europeanyachtbrokers.com/wp-content/uploads/2026/01/33.jpg",
      "width": 1920,
      "height": 1080
    },
    {
      "id": 146303,
      "url": "https://europeanyachtbrokers.com/wp-content/uploads/2026/01/32.jpg",
      "width": 1920,
      "height": 1080
    },
    {
      "id": 146302,
      "url": "https://europeanyachtbrokers.com/wp-content/uploads/2026/01/31.jpg",
      "width": 1920,
      "height": 1080
    },
    {
      "id": 146301,
      "url": "https://europeanyachtbrokers.com/wp-content/uploads/2026/01/30.jpg",
      "width": 1920,
      "height": 1080
    },
    {
      "id": 146300,
      "url": "https://europeanyachtbrokers.com/wp-content/uploads/2026/01/29.jpg",
      "width": 1920,
      "height": 1080
    },
    {
      "id": 146299,
      "url": "https://europeanyachtbrokers.com/wp-content/uploads/2026/01/28.jpg",
      "width": 1920,
      "height": 1080
    },
    {
      "id": 146298,
      "url": "https://europeanyachtbrokers.com/wp-content/uploads/2026/01/27.jpg",
      "width": 1920,
      "height": 1080
    },
    {
      "id": 146297,
      "url": "https://europeanyachtbrokers.com/wp-content/uploads/2026/01/26.jpg",
      "width": 1920,
      "height": 1080
    },
    {
      "id": 146296,
      "url": "https://europeanyachtbrokers.com/wp-content/uploads/2026/01/25.jpg",
      "width": 1920,
      "height": 1080
    },
    {
      "id": 146295,
      "url": "https://europeanyachtbrokers.com/wp-content/uploads/2026/01/24.jpg",
      "width": 1920,
      "height": 1080
    },
    {
      "id": 146294,
      "url": "https://europeanyachtbrokers.com/wp-content/uploads/2026/01/23.jpg",
      "width": 1920,
      "height": 1080
    },
    {
      "id": 146293,
      "url": "https://europeanyachtbrokers.com/wp-content/uploads/2026/01/22.jpg",
      "width": 1920,
      "height": 1080
    },
    {
      "id": 146292,
      "url": "https://europeanyachtbrokers.com/wp-content/uploads/2026/01/21.jpg",
      "width": 1920,
      "height": 1080
    },
    {
      "id": 146291,
      "url": "https://europeanyachtbrokers.com/wp-content/uploads/2026/01/20.jpg",
      "width": 1920,
      "height": 1080
    },
    {
      "id": 146290,
      "url": "https://europeanyachtbrokers.com/wp-content/uploads/2026/01/19.jpg",
      "width": 1920,
      "height": 1080
    },
    {
      "id": 146289,
      "url": "https://europeanyachtbrokers.com/wp-content/uploads/2026/01/18.jpg",
      "width": 1920,
      "height": 1080
    },
    {
      "id": 146288,
      "url": "https://europeanyachtbrokers.com/wp-content/uploads/2026/01/17.jpg",
      "width": 1920,
      "height": 1080
    },
    {
      "id": 146287,
      "url": "https://europeanyachtbrokers.com/wp-content/uploads/2026/01/16.jpg",
      "width": 1920,
      "height": 1080
    },
    {
      "id": 146286,
      "url": "https://europeanyachtbrokers.com/wp-content/uploads/2026/01/15.jpg",
      "width": 1920,
      "height": 1080
    },
    {
      "id": 146285,
      "url": "https://europeanyachtbrokers.com/wp-content/uploads/2026/01/14.jpg",
      "width": 1920,
      "height": 1080
    },
    {
      "id": 146284,
      "url": "https://europeanyachtbrokers.com/wp-content/uploads/2026/01/13.jpg",
      "width": 1920,
      "height": 1080
    },
    {
      "id": 146283,
      "url": "https://europeanyachtbrokers.com/wp-content/uploads/2026/01/12.jpg",
      "width": 1920,
      "height": 1080
    },
    {
      "id": 146282,
      "url": "https://europeanyachtbrokers.com/wp-content/uploads/2026/01/11-1.jpg",
      "width": 1920,
      "height": 1080
    },
    {
      "id": 146281,
      "url": "https://europeanyachtbrokers.com/wp-content/uploads/2026/01/10-1.jpg",
      "width": 1920,
      "height": 1080
    },
    {
      "id": 146280,
      "url": "https://europeanyachtbrokers.com/wp-content/uploads/2026/01/9-1.jpg",
      "width": 1920,
      "height": 1080
    },
    {
      "id": 146279,
      "url": "https://europeanyachtbrokers.com/wp-content/uploads/2026/01/8-1.jpg",
      "width": 1920,
      "height": 1080
    },
    {
      "id": 146278,
      "url": "https://europeanyachtbrokers.com/wp-content/uploads/2026/01/7-1.jpg",
      "width": 1920,
      "height": 1080
    },
    {
      "id": 146277,
      "url": "https://europeanyachtbrokers.com/wp-content/uploads/2026/01/6-1.jpg",
      "width": 1920,
      "height": 1080
    },
    {
      "id": 146276,
      "url": "https://europeanyachtbrokers.com/wp-content/uploads/2026/01/5-1.jpg",
      "width": 1920,
      "height": 1080
    },
    {
      "id": 146275,
      "url": "https://europeanyachtbrokers.com/wp-content/uploads/2026/01/4-1.jpg",
      "width": 1920,
      "height": 1080
    },
    {
      "id": 146274,
      "url": "https://europeanyachtbrokers.com/wp-content/uploads/2026/01/3-1.jpg",
      "width": 1920,
      "height": 1080
    },
    {
      "id": 146273,
      "url": "https://europeanyachtbrokers.com/wp-content/uploads/2026/01/2-1.jpg",
      "width": 1920,
      "height": 1080
    }
  ]
}