{
  "eybSlug": "grand-soleil-40-for-sale-2005",
  "method": "slug",
  "sourceUrl": "https://europeanyachtbrokers.com/yachts/grand-soleil-40-for-sale-2005/",
  "wpPostId": 153870,
  "descriptionText": "Grand Soleil 40 for sale 2005 | 3 Cabins VersionIf you’re considering a reliable and comfortable cruiser, the Grand Soleil 40 for sale 2005 offers a good opportunity. Available in Liguria, this Italian-flagged yacht provides a balance of performance and user-friendly features, and she is in good condition, benefiting from careful ownership and regular maintenance.General SpecificationsModel: Grand Soleil 40Year of Construction: 2005Year of Registration: 2006Hull Length: 11.99 metresOverall Length: 12.29 metresBeam: 3.76 metresDraft: 2.15 metresDisplacement: Not specifiedMaximum Speed: 8 knotsCruising Speed: 7 knotsFlag: ItalianVisibility: LiguriaHull Material: VTR (fibreglass)Deck: GRP + TeakInterior LayoutCabins: 3 (Bow cabin with exclusive bathroom, two aft cabins)Heads (Bathrooms): 2 (Bathroom in the bow and on the left side of the stern)Galley: Located on the port side (left)Heating: Webasto heatingSails and Deck EquipmentDacron MainsailDacron GenoaLazy bag and lazy jack (for easier sail handling)BiminiSprayhoodTender includedCatwalkRaftRina Safety Certificate: Valid until 2029Engine and Technical FeaturesEngine: Yanmar 3JH4CE, 40hpFuel Type: DieselTransmission: SdriveTank Capacity: 180 litres (fuel)Water Tank: 370 litresBoiler: Electric and motor-poweredAutoclave: PresentElectrical SystemsVoltage: 12-220VBatteries: 6 (installed in 2022)Battery Charger: Present (new Quick charger with remote display on chart table)Navigation & ElectronicsComplete Raymarine InstrumentationRadarRaymarine Autopilot (with wireless remote control)Raymarine C80 Cartographic GPSWind, Speed, Graphics instrumentation (Raymarine)Raymarine VHF (new)Additional DetailsCertification Expiry: 2029 (Rina safety certificate)Desalination Plant: Not presentOverall, the Grand Soleil 40 for sale 2005 is ready for her next owner. She is well-maintained, thoughtfully equipped, and offers practical cruising features without unnecessary sophistication. For viewing arrangements or further details, inquiries are welcome.",
  "descriptionHtml": "<h4 style=\"text-align: center\"><strong>Grand Soleil 40 for sale 2005 | 3 Cabins Version</strong></h4><p>If you’re considering a reliable and comfortable cruiser, the <strong>Grand Soleil 40 for sale 2005</strong> offers a good opportunity. Available in Liguria, this Italian-flagged yacht provides a balance of performance and user-friendly features, and she is in good condition, benefiting from careful ownership and regular maintenance.</p><p><strong>General Specifications</strong></p><ul><li><strong>Model:</strong> Grand Soleil 40</li><li><strong>Year of Construction:</strong> 2005</li><li><strong>Year of Registration:</strong> 2006</li><li><strong>Hull Length:</strong> 11.99 metres</li><li><strong>Overall Length:</strong> 12.29 metres</li><li><strong>Beam:</strong> 3.76 metres</li><li><strong>Draft:</strong> 2.15 metres</li><li><strong>Displacement:</strong> Not specified</li><li><strong>Maximum Speed:</strong> 8 knots</li><li><strong>Cruising Speed:</strong> 7 knots</li><li><strong>Flag:</strong> Italian</li><li><strong>Visibility:</strong> Liguria</li><li><strong>Hull Material:</strong> VTR (fibreglass)</li><li><strong>Deck:</strong> GRP + Teak</li></ul><p><strong>Interior Layout</strong></p><ul><li><strong>Cabins:</strong> 3 (Bow cabin with exclusive bathroom, two aft cabins)</li><li><strong>Heads (Bathrooms):</strong> 2 (Bathroom in the bow and on the left side of the stern)</li><li><strong>Galley:</strong> Located on the port side (left)</li><li><strong>Heating:</strong> Webasto heating</li></ul><p><strong>Sails and Deck Equipment</strong></p><ul><li><strong>Dacron Mainsail</strong></li><li><strong>Dacron Genoa</strong></li><li><strong>Lazy bag and lazy jack (for easier sail handling)</strong></li><li><strong>Bimini</strong></li><li><strong>Sprayhood</strong></li><li><strong>Tender included</strong></li><li><strong>Catwalk</strong></li><li><strong>Raft</strong></li><li><strong>Rina Safety Certificate:</strong> Valid until 2029</li></ul><p><strong>Engine and Technical Features</strong></p><ul><li><strong>Engine:</strong> Yanmar 3JH4CE, 40hp</li><li><strong>Fuel Type:</strong> Diesel</li><li><strong>Transmission:</strong> Sdrive</li><li><strong>Tank Capacity:</strong> 180 litres (fuel)</li><li><strong>Water Tank:</strong> 370 litres</li><li><strong>Boiler:</strong> Electric and motor-powered</li><li><strong>Autoclave:</strong> Present</li></ul><p><strong>Electrical Systems</strong></p><ul><li><strong>Voltage:</strong> 12-220V</li><li><strong>Batteries:</strong> 6 (installed in 2022)</li><li><strong>Battery Charger:</strong> Present (new Quick charger with remote display on chart table)</li></ul><p><strong>Navigation &amp; Electronics</strong></p><ul><li><strong>Complete Raymarine Instrumentation</strong></li><li><strong>Radar</strong></li><li><strong>Raymarine Autopilot (with wireless remote control)</strong></li><li><strong>Raymarine C80 Cartographic GPS</strong></li><li><strong>Wind, Speed, Graphics instrumentation (Raymarine)</strong></li><li><strong>Raymarine VHF (new)</strong></li></ul><p><strong>Additional Details</strong></p><ul><li><strong>Certification Expiry:</strong> 2029 (Rina safety certificate)</li><li><strong>Desalination Plant:</strong> Not present</li></ul><p>Overall, the <strong>Grand Soleil 40 for sale 2005</strong> is ready for her next owner. She is well-maintained, thoughtfully equipped, and offers practical cruising features without unnecessary sophistication. For viewing arrangements or further details, inquiries are welcome.</p>",
  "features": [
    "autopilot",
    "depth-sounder",
    "gps",
    "log-speedometer",
    "navigation-centre",
    "radar",
    "vhf",
    "wind-speed-and-direction",
    "battery-charger",
    "heating",
    "liferaft",
    "tender",
    "furling-mainsail"
  ],
  "featuredImage": "https://europeanyachtbrokers.com/wp-content/uploads/2026/02/1-30.jpg",
  "images": [
    {
      "id": 153903,
      "url": "https://europeanyachtbrokers.com/wp-content/uploads/2026/02/1-30.jpg",
      "width": 1920,
      "height": 1080
    },
    {
      "id": 153901,
      "url": "https://europeanyachtbrokers.com/wp-content/uploads/2026/02/23-6.jpg",
      "width": 1920,
      "height": 1080
    },
    {
      "id": 153900,
      "url": "https://europeanyachtbrokers.com/wp-content/uploads/2026/02/22-6.jpg",
      "width": 1920,
      "height": 1080
    },
    {
      "id": 153895,
      "url": "https://europeanyachtbrokers.com/wp-content/uploads/2026/02/21-6.jpg",
      "width": 1920,
      "height": 1080
    },
    {
      "id": 153892,
      "url": "https://europeanyachtbrokers.com/wp-content/uploads/2026/02/20-7.jpg",
      "width": 1920,
      "height": 1080
    },
    {
      "id": 153891,
      "url": "https://europeanyachtbrokers.com/wp-content/uploads/2026/02/19-8.jpg",
      "width": 1920,
      "height": 1080
    },
    {
      "id": 153890,
      "url": "https://europeanyachtbrokers.com/wp-content/uploads/2026/02/18-8.jpg",
      "width": 1920,
      "height": 1080
    },
    {
      "id": 153889,
      "url": "https://europeanyachtbrokers.com/wp-content/uploads/2026/02/17-8.jpg",
      "width": 1920,
      "height": 1080
    },
    {
      "id": 153888,
      "url": "https://europeanyachtbrokers.com/wp-content/uploads/2026/02/16-8.jpg",
      "width": 1920,
      "height": 1080
    },
    {
      "id": 153887,
      "url": "https://europeanyachtbrokers.com/wp-content/uploads/2026/02/15-8.jpg",
      "width": 1920,
      "height": 1080
    },
    {
      "id": 153886,
      "url": "https://europeanyachtbrokers.com/wp-content/uploads/2026/02/14-9.jpg",
      "width": 1920,
      "height": 1080
    },
    {
      "id": 153885,
      "url": "https://europeanyachtbrokers.com/wp-content/uploads/2026/02/13-9.jpg",
      "width": 1920,
      "height": 1080
    },
    {
      "id": 153884,
      "url": "https://europeanyachtbrokers.com/wp-content/uploads/2026/02/12-9.jpg",
      "width": 1920,
      "height": 1080
    },
    {
      "id": 153883,
      "url": "https://europeanyachtbrokers.com/wp-content/uploads/2026/02/11-9.jpg",
      "width": 1920,
      "height": 1080
    },
    {
      "id": 153882,
      "url": "https://europeanyachtbrokers.com/wp-content/uploads/2026/02/10-11.jpg",
      "width": 1920,
      "height": 1080
    },
    {
      "id": 153881,
      "url": "https://europeanyachtbrokers.com/wp-content/uploads/2026/02/9-11.jpg",
      "width": 1920,
      "height": 1080
    },
    {
      "id": 153880,
      "url": "https://europeanyachtbrokers.com/wp-content/uploads/2026/02/8-12.jpg",
      "width": 1920,
      "height": 1080
    },
    {
      "id": 153879,
      "url": "https://europeanyachtbrokers.com/wp-content/uploads/2026/02/7-12.jpg",
      "width": 1920,
      "height": 1080
    },
    {
      "id": 153878,
      "url": "https://europeanyachtbrokers.com/wp-content/uploads/2026/02/6-12.jpg",
      "width": 1920,
      "height": 1080
    },
    {
      "id": 153877,
      "url": "https://europeanyachtbrokers.com/wp-content/uploads/2026/02/5-12.jpg",
      "width": 1920,
      "height": 1080
    },
    {
      "id": 153876,
      "url": "https://europeanyachtbrokers.com/wp-content/uploads/2026/02/4-12.jpg",
      "width": 1920,
      "height": 1080
    },
    {
      "id": 153875,
      "url": "https://europeanyachtbrokers.com/wp-content/uploads/2026/02/3-13.jpg",
      "width": 1920,
      "height": 1080
    },
    {
      "id": 153874,
      "url": "https://europeanyachtbrokers.com/wp-content/uploads/2026/02/2-14.jpg",
      "width": 1920,
      "height": 1080
    }
  ]
}